dicomautomaton/__init__.py
dicomautomaton-0.1.0.dist-info/WHEEL
dicomautomaton-0.1.0.dist-info/METADATA
dicomautomaton-0.1.0.dist-info/RECORD
